[{"scan_code": 45, "time": 53, "type": "up"}, {"scan_code": 49, "time": 117, "type": "down"}, {"scan_code": 49, "time": 197, "type": "up"}, {"scan_code": 32, "time": 261, "type": "down"}, {"scan_code": 32, "time": 357, "type": "up"}, {"scan_code": 35, "time": 453, "type": "down"}, {"scan_code": 2, "time": 517, "type": "down"}, {"scan_code": 35, "time": 549, "type": "up"}, {"scan_code": 2, "time": 613, "type": "up"}, {"scan_code": 0, "time": 709, "type": "down"}, {"scan_code": 0, "time": 780, "type": "up"}, {"scan_code": 17, "time": 885, "type": "down"}, {"scan_code": 14, "time": 926, "type": "down"}, {"scan_code": 17, "time": 981, "type": "up"}]