[{"scan_code": 51, "time": 27, "type": "down"}, {"scan_code": 15, "time": 107, "type": "down"}, {"scan_code": 51, "time": 108, "type": "up"}, {"scan_code": 14, "time": 187, "type": "down"}, {"scan_code": 15, "time": 227, "type": "up"}, {"scan_code": 14, "time": 266, "type": "up"}, {"scan_code": 0, "time": 411, "type": "down"}, {"scan_code": 0, "time": 483, "type": "up"}, {"scan_code": 17, "time": 635, "type": "down"}, {"scan_code": 14, "time": 717, "type": "down"}, {"scan_code": 17, "time": 795, "type": "up"}, {"scan_code": 60, "time": 827, "type": "down"}, {"scan_code": 14, "time": 828, "type": "up"}, {"scan_code": 46, "time": 931, "type": "down"}]