[{"scan_code": 105, "time": -1, "type": "down"}, {"scan_code": 105, "time": 82, "type": "down"}, {"scan_code": 105, "time": 166, "type": "down"}, {"scan_code": 105, "time": 250, "type": "down"}, {"scan_code": 105, "time": 334, "type": "down"}, {"scan_code": 105, "time": 419, "type": "down"}, {"scan_code": 105, "time": 503, "type": "down"}, {"scan_code": 105, "time": 588, "type": "down"}, {"scan_code": 105, "time": 671, "type": "down"}, {"scan_code": 105, "time": 755, "type": "down"}, {"scan_code": 105, "time": 840, "type": "down"}, {"scan_code": 105, "time": 924, "type": "down"}]