[{"scan_code": 0, "time": 46, "type": "down"}, {"scan_code": 0, "time": 130, "type": "down"}, {"scan_code": 0, "time": 213, "type": "down"}, {"scan_code": 0, "time": 298, "type": "down"}, {"scan_code": 0, "time": 382, "type": "down"}, {"scan_code": 0, "time": 466, "type": "down"}, {"scan_code": 0, "time": 550, "type": "down"}, {"scan_code": 0, "time": 634, "type": "down"}, {"scan_code": 0, "time": 717, "type": "down"}, {"scan_code": 0, "time": 802, "type": "down"}, {"scan_code": 0, "time": 886, "type": "down"}, {"scan_code": 0, "time": 970, "type": "down"}]