[{"scan_code": 29, "time": 26, "type": "down"}, {"scan_code": 29, "time": 109, "type": "down"}, {"scan_code": 29, "time": 193, "type": "down"}, {"scan_code": 29, "time": 278, "type": "down"}, {"scan_code": 29, "time": 362, "type": "down"}, {"scan_code": 29, "time": 445, "type": "down"}, {"scan_code": 29, "time": 528, "type": "down"}, {"scan_code": 29, "time": 612, "type": "down"}, {"scan_code": 29, "time": 697, "type": "down"}, {"scan_code": 29, "time": 781, "type": "down"}, {"scan_code": 29, "time": 865, "type": "down"}, {"scan_code": 29, "time": 950, "type": "down"}]