[{"scan_code": 49, "time": 69, "type": "down"}, {"scan_code": 49, "time": 153, "type": "down"}, {"scan_code": 49, "time": 237, "type": "down"}, {"scan_code": 49, "time": 322, "type": "down"}, {"scan_code": 49, "time": 405, "type": "down"}, {"scan_code": 49, "time": 489, "type": "down"}, {"scan_code": 49, "time": 572, "type": "down"}, {"scan_code": 49, "time": 656, "type": "down"}, {"scan_code": 49, "time": 740, "type": "down"}, {"scan_code": 49, "time": 823, "type": "down"}, {"scan_code": 49, "time": 906, "type": "down"}, {"scan_code": 49, "time": 990, "type": "down"}]