[{"scan_code": 51, "time": 58, "type": "down"}, {"scan_code": 24, "time": 58, "type": "down"}, {"scan_code": 30, "time": 59, "type": "down"}, {"scan_code": 36, "time": 81, "type": "down"}, {"scan_code": 36, "time": 583, "type": "down"}, {"scan_code": 36, "time": 666, "type": "down"}, {"scan_code": 24, "time": 730, "type": "up"}, {"scan_code": 36, "time": 751, "type": "down"}, {"scan_code": 51, "time": 785, "type": "up"}, {"scan_code": 30, "time": 786, "type": "up"}, {"scan_code": 36, "time": 801, "type": "up"}]