[{"scan_code": 45, "time": 0, "type": "down"}, {"scan_code": 45, "time": 84, "type": "down"}, {"scan_code": 56, "time": 111, "type": "down"}, {"scan_code": 11, "time": 131, "type": "up"}, {"scan_code": 45, "time": 163, "type": "up"}, {"scan_code": 57, "time": 325, "type": "down"}, {"scan_code": 126, "time": 469, "type": "down"}, {"scan_code": 126, "time": 565, "type": "up"}, {"scan_code": 56, "time": 768, "type": "up"}, {"scan_code": 97, "time": 805, "type": "down"}, {"scan_code": 28, "time": 821, "type": "down"}]