[{"scan_code": 49, "time": 1578322958.1542451, "type": "down"}, {"scan_code": 49, "time": 1578322958.236604, "type": "down"}, {"scan_code": 49, "time": 1578322958.319672, "type": "down"}, {"scan_code": 49, "time": 1578322958.402928, "type": "down"}, {"scan_code": 49, "time": 1578322958.486838, "type": "down"}, {"scan_code": 49, "time": 1578322958.570834, "type": "down"}, {"scan_code": 49, "time": 1578322958.65398, "type": "down"}, {"scan_code": 49, "time": 1578322958.737809, "type": "down"}, {"scan_code": 49, "time": 1578322958.821884, "type": "down"}, {"scan_code": 49, "time": 1578322958.849895, "type": "up"}, {"scan_code": 13, "time": 1578322959.110802, "type": "down"}]