[{"scan_code": 49, "time": 71, "type": "down"}, {"scan_code": 49, "time": 155, "type": "down"}, {"scan_code": 49, "time": 239, "type": "down"}, {"scan_code": 49, "time": 325, "type": "down"}, {"scan_code": 49, "time": 407, "type": "down"}, {"scan_code": 49, "time": 492, "type": "down"}, {"scan_code": 49, "time": 575, "type": "down"}, {"scan_code": 49, "time": 659, "type": "down"}, {"scan_code": 49, "time": 743, "type": "down"}, {"scan_code": 49, "time": 827, "type": "down"}, {"scan_code": 49, "time": 911, "type": "down"}, {"scan_code": 69, "time": 959, "type": "up"}, {"scan_code": 49, "time": 995, "type": "down"}]