[{"scan_code": 45, "time": 21, "type": "down"}, {"scan_code": 45, "time": 105, "type": "down"}, {"scan_code": 45, "time": 189, "type": "down"}, {"scan_code": 45, "time": 273, "type": "down"}, {"scan_code": 45, "time": 358, "type": "down"}, {"scan_code": 45, "time": 442, "type": "down"}, {"scan_code": 45, "time": 525, "type": "down"}, {"scan_code": 45, "time": 609, "type": "down"}, {"scan_code": 45, "time": 694, "type": "down"}, {"scan_code": 45, "time": 778, "type": "down"}, {"scan_code": 45, "time": 862, "type": "down"}, {"scan_code": 60, "time": 868, "type": "down"}, {"scan_code": 3, "time": 868, "type": "down"}, {"scan_code": 45, "time": 868, "type": "up"}, {"scan_code": 9, "time": 868, "type": "down"}]